pylexis/__init__.py
pylexis/common.py
pylexis-0.1.3.dist-info/LICENSE
pylexis-0.1.3.dist-info/METADATA
pylexis-0.1.3.dist-info/WHEEL
pylexis-0.1.3.dist-info/top_level.txt
pylexis-0.1.3.dist-info/RECORD
