Metadata-Version: 2.1
Name: pylexis
Version: 0.1.3
Summary: Quickly and easily draw basic Lexis diagrams
Home-page: https://github.com/cacrespo/pylexis
Author: Carlos A. Crespo
Author-email: lvccrespo@gmail.com
License: MIT
Classifier: Programming Language :: Python :: 3
Classifier: License :: OSI Approved :: MIT License
Classifier: Operating System :: OS Independent
Requires-Python: >=3.6
License-File: LICENSE
Requires-Dist: matplotlib
